Metadata-Version: 1.1
Name: iamchrise-distributions
Version: 1.0
Summary: Gaussian and Binomial distributions
Home-page: https://github.com/emichris/Distribution-Pakage-Files
Author: Christian Emiyah
Author-email: christian.emiyah@gmail.com
License: UNKNOWN
Platform: UNKNOWN
Classifier: Programming Language :: Python :: 3
Classifier: License :: OSI Approved :: MIT License
Classifier: Operating System :: OS Independent
